bot_hosting_wrapper/__init__.py
bot_hosting_wrapper/about.py
bot_hosting_wrapper/interactive.py
bot_hosting_wrapper/panel.py
bot_hosting_wrapper/vasync/about.py
bot_hosting_wrapper-1.4.dist-info/licenses/LICENSE
bot_hosting_wrapper-1.4.dist-info/METADATA
bot_hosting_wrapper-1.4.dist-info/WHEEL
bot_hosting_wrapper-1.4.dist-info/top_level.txt
bot_hosting_wrapper-1.4.dist-info/RECORD
