Metadata-Version: 2.4
Name: bot_hosting_wrapper
Version: 1.4
Summary: A simple API Wrapper for bot-hosting.net
Author: Bubblegum
Project-URL: Repository, https://github.com/suspectedesp/bot-hosting-wrapper/
Project-URL: Bot-Hosting, https://bot-hosting.net/
Classifier: Programming Language :: Python :: 3.10
Classifier: License :: Public Domain
Classifier: Operating System :: OS Independent
Requires-Python: >=3.8
License-File: LICENSE
Requires-Dist: requests>=2.26.0
Requires-Dist: colorama>=0.4.4
Requires-Dist: aiohttp>=3.10.5
Dynamic: license-file
